hmx2/__init__.py
hmx2/constants.py
hmx2/enum.py
hmx2/hmx_client.py
hmx2/abis/AdaptiveFeeCalculator.json
hmx2/abis/CIXPriceAdapter.json
hmx2/abis/CalcPricelens.json
hmx2/abis/Calculator.json
hmx2/abis/ConfigStorage.json
hmx2/abis/CrossMarginHandler.json
hmx2/abis/ERC20.json
hmx2/abis/GlpManager.json
hmx2/abis/GmPriceAdapter.json
hmx2/abis/LimitTradeHandler.json
hmx2/abis/OnchainPricelens.json
hmx2/abis/OrderbookOracle.json
hmx2/abis/PerpStorage.json
hmx2/abis/TradeHelper.json
hmx2/abis/VaultStorage.json
hmx2/constants/__init__.py
hmx2/constants/assets.py
hmx2/constants/common.py
hmx2/constants/contracts.py
hmx2/constants/intent.py
hmx2/constants/markets.py
hmx2/constants/pricefeed.py
hmx2/constants/tokens.py
hmx2/helpers/__init__.py
hmx2/helpers/contract_loader.py
hmx2/helpers/mapper.py
hmx2/helpers/util.py
hmx2/modules/__init__.py
hmx2/modules/private.py
hmx2/modules/public.py
hmx2/modules/calculator/__init__.py
hmx2/modules/calculator/calculator.py
hmx2/modules/oracle/__init__.py
hmx2/modules/oracle/oracle_middleware.py
hmx2/modules/oracle/calc_pricelens_oracle/__init__.py
hmx2/modules/oracle/calc_pricelens_oracle/calc_pricelens_oracle.py
hmx2/modules/oracle/cix_oracle/__init__.py
hmx2/modules/oracle/cix_oracle/cix_oracle.py
hmx2/modules/oracle/glp_oracle/__init__.py
hmx2/modules/oracle/glp_oracle/glp_oracle.py
hmx2/modules/oracle/gm_oracle/__init__.py
hmx2/modules/oracle/gm_oracle/gm_oracle.py
hmx2/modules/oracle/onchain_pricelens_oracle/__init__.py
hmx2/modules/oracle/onchain_pricelens_oracle/onchain_pricelen_oracle.py
hmx2/modules/oracle/pyth_oracle/__init__.py
hmx2/modules/oracle/pyth_oracle/constants.py
hmx2/modules/oracle/pyth_oracle/pyth_oracle.py
tests/__init__.py
tests/constants.py
tests/test_create_market_order.py
tests/test_deposit_collateral.py
tests/test_get_adaptive_fee.py
tests/test_init.py
hmx_v2_python_test-1.2.3.dist-info/LICENSE
hmx_v2_python_test-1.2.3.dist-info/METADATA
hmx_v2_python_test-1.2.3.dist-info/WHEEL
hmx_v2_python_test-1.2.3.dist-info/top_level.txt
hmx_v2_python_test-1.2.3.dist-info/RECORD
