Metadata-Version: 2.1
Name: hmx-v2-python-test
Version: 1.2.3
Summary: HMXv2 Python SDK
Home-page: https://github.com/HMXOrg/v2-sdk-python
Author: HMXOrg
Author-email: contact@hmx.org
License: MIT
Keywords: hmx exchange perp dex defi ethereum eth arbitrum
Classifier: Intended Audience :: Developers
Classifier: License :: OSI Approved :: MIT License
Classifier: Operating System :: OS Independent
Classifier: Programming Language :: Python :: 2
Classifier: Programming Language :: Python :: 2.7
Classifier: Programming Language :: Python :: 3
Classifier: Programming Language :: Python :: 3.4
Classifier: Programming Language :: Python :: 3.5
Classifier: Programming Language :: Python :: 3.6
Classifier: Programming Language :: Python :: 3.9
Classifier: Programming Language :: Python :: 3.11
Classifier: Programming Language :: Python
Classifier: Topic :: Software Development :: Libraries :: Python Modules
License-File: LICENSE
Requires-Dist: eth-keys ==0.5.0
Requires-Dist: eth-account ==0.10.0
Requires-Dist: eth-abi <5.0.0,>=4.0.0
Requires-Dist: uniswap-universal-router-decoder
Requires-Dist: web3 <7.0.0,>=6.0.0
Requires-Dist: simple-multicall-v6
Requires-Dist: responses
Requires-Dist: python-dotenv >=1.0.0
